connect_n/__init__.py
connect_n/ai.py
connect_n/connect_n.py
connect_n/env.py
connect_n/player.py
connect_n/pygame_utility.py
connect_n/utility.py
connect_n/ai_nn/__init__.py
connect_n/ai_nn/generate_data.py
connect_n/ai_nn/preprocess.py
connect_n/api/__init__.py
connect_n/api/app.py
connect_n/api/auth.py
connect_n/api/db_model.py
connect_n/api/env.py
connect_n/api/error.py
connect_n/api/routes.py
connect_n/api/tokens.py
connect_n/api/utility.py
connect_n-0.0.5.dist-info/LICENSE
connect_n-0.0.5.dist-info/METADATA
connect_n-0.0.5.dist-info/WHEEL
connect_n-0.0.5.dist-info/top_level.txt
connect_n-0.0.5.dist-info/RECORD
