Metadata-Version: 2.1
Name: connect-n
Version: 0.0.5
Summary: A modified version of Connect-4 game implemented with AI using PyGame.
Home-page: https://github.com/Kartikei-12/Connect-N
Author: Kartikei Mittal
Author-email: kartikeimittal@gmail.com
License: UNKNOWN
Platform: UNKNOWN
Classifier: Programming Language :: Python :: 3
Classifier: License :: OSI Approved :: GNU General Public License v3 (GPLv3)
Classifier: Operating System :: OS Independent
Requires-Dist: numpy
Requires-Dist: loguru
Requires-Dist: pygame
Requires-Dist: html-testRunner
